{
 "actions": [],
 "creation": "2020-01-10 16:11:30.386607",
 "doctype": "DocType",
 "editable_grid": 1,
 "engine": "InnoDB",
 "field_order": [
  "size"
 ],
 "fields": [
  {
   "fieldname": "size",
   "fieldtype": "Link",
   "in_list_view": 1,
   "label": "Size",
   "options": "Apparelo Size",
   "reqd": 1
  }
 ],
 "istable": 1,
 "links": [],
 "modified": "2020-01-23 16:04:05.826434",
 "modified_by": "Administrator",
 "module": "Apparelo",
 "name": "Cutting Size",
 "owner": "Administrator",
 "permissions": [],
 "quick_entry": 1,
 "sort_field": "modified",
 "sort_order": "DESC",
 "track_changes": 1
}